[
{"args":0.5,"effect":"sfx","value":"blackscreenunfade"},
{"effect":"music","value":"eventgeneric"},
{"delay":0.5,"effect":"background","value":"villageday"},
{"effect":"gui","value":"gui_normal"},
{"args":0.5,"delay":0.5,"effect":"sfx","value":"blackscreenfade"},
{"effect":"text","portrait":"ArronSmile","sound":null,"source":"ARRON","value":"demitrius 1.json_1"},
{"effect":"text","portrait":"RoseNormal","sound":null,"source":"ROSE","value":"demitrius 1.json_2"},
{"effect":"text","portrait":"ArronSmile","sound":null,"source":"ARRON","value":"demitrius 1.json_3"},
{"args":"goblin","effect":"sprite","value":"set"},
{"args":0.5,"effect":"sprite","value":"unfade"},
{"effect":"text","portrait":"goblin","sound":null,"source":"GOBLIN","value":"demitrius 1.json_4"},
{"effect":"text","portrait":"ArronSmile","sound":null,"source":"ARRON","value":"demitrius 1.json_5"},
{"effect":"text","portrait":"RoseNormal","sound":null,"source":"ROSE","value":"demitrius 1.json_6"},
{"effect":"text","portrait":"ArronSmile","sound":null,"source":"ARRON","value":"demitrius 1.json_7"},
{"effect":"text","portrait":"goblin","sound":null,"source":"GOBLIN","value":"demitrius 1.json_8"},
{"args":0.5,"effect":"sprite","value":"fade"},
{"effect":"text","portrait":"ArronSmile","sound":null,"source":"ARRON","value":"demitrius 1.json_9"},
{"effect":"text","portrait":"RoseSarcastic","sound":null,"source":"ROSE","value":"demitrius 1.json_10"},
{"effect":"text","portrait":"ArronSmile","sound":null,"source":"ARRON","value":"demitrius 1.json_11"},
{"effect":"text","portrait":"RoseNormal","sound":null,"source":"ROSE","value":"demitrius 1.json_12"},
{"effect":"gui","value":"gui_hide"},
{"args":1,"delay":0.5,"effect":"sfx","value":"blackscreentransition"},
{"args":"demitrius","effect":"sprite","value":"set"},
{"args":0.5,"effect":"sprite","value":"unfade"},
{"effect":"gui","value":"gui_normal"},
{"effect":"text","portrait":"Demitrius","sound":null,"source":"DEMITRIUS","value":"demitrius 1.json_13"},
{"effect":"text","portrait":"Demitrius","sound":null,"source":"DEMITRIUS","value":"demitrius 1.json_14"},
{"effect":"text","portrait":"RoseNormal","sound":null,"source":"ROSE","value":"demitrius 1.json_15"},
{"effect":"text","portrait":"ArronSmile","sound":null,"source":"ARRON","value":"demitrius 1.json_16"},
{"effect":"text","portrait":"Demitrius","sound":null,"source":"DEMITRIUS","value":"demitrius 1.json_17"},
{"effect":"text","portrait":null,"sound":null,"source":"narrator","value":"demitrius 1.json_18"},
{"effect":"choice","value":[{"index":0,"text":"Listen obediently"},{"index":1,"text":"Listen disinterestedly"}]},
{"effect":"skip","log":"LISTEN OBEDIENTLY","value":1},
{"effect":"skip","log":"LISTEN DISINTERESTEDLY","value":0},
{"effect":"text","portrait":"Demitrius","sound":null,"source":"DEMITRIUS","value":"demitrius 1.json_19"},
{"effect":"text","portrait":"ArronSmile","sound":null,"source":"ARRON","value":"demitrius 1.json_20"},
{"effect":"text","portrait":"Demitrius","sound":null,"source":"DEMITRIUS","value":"demitrius 1.json_21"},
{"effect":"text","portrait":"RoseNormal","sound":null,"source":"ROSE","value":"demitrius 1.json_22"},
{"effect":"text","portrait":"Demitrius","sound":null,"source":"DEMITRIUS","value":"demitrius 1.json_23"},
{"effect":"text","portrait":"Demitrius","sound":null,"source":"DEMITRIUS","value":"demitrius 1.json_24"},
{"effect":"text","portrait":"RoseNormal","sound":null,"source":"ROSE","value":"demitrius 1.json_25"},
{"effect":"text","portrait":"ArronSmile","sound":null,"source":"ARRON","value":"demitrius 1.json_26"},
{"effect":"text","portrait":"ArronSmile","sound":null,"source":"ARRON","value":"demitrius 1.json_27"},
{"effect":"text","portrait":"Demitrius","sound":null,"source":"DEMITRIUS","value":"demitrius 1.json_28"},
{"effect":"text","portrait":"ArronSmile","sound":null,"source":"ARRON","value":"demitrius 1.json_29"},
{"effect":"text","portrait":"Demitrius","sound":null,"source":"DEMITRIUS","value":"demitrius 1.json_30"},
{"effect":"text","portrait":"Demitrius","sound":null,"source":"DEMITRIUS","value":"demitrius 1.json_31"},
{"effect":"text","portrait":"RoseNormal","sound":null,"source":"ROSE","value":"demitrius 1.json_32"},
{"effect":"text","portrait":"goblin","sound":null,"source":"GOBLIN","value":"demitrius 1.json_33"},
{"effect":"text","portrait":"ArronSmile","sound":null,"source":"ARRON","value":"demitrius 1.json_34"},
{"effect":"text","portrait":"ArronSmile","sound":null,"source":"ARRON","value":"demitrius 1.json_35"},
{"effect":"text","portrait":"Demitrius","sound":null,"source":"DEMITRIUS","value":"demitrius 1.json_36"},
{"effect":"stop","value":""}
]
